LICENSE
README.md
setup.py
sw_rest_utils/__init__.py
sw_rest_utils/generics.py
sw_rest_utils/middleware.py
sw_rest_utils/renderers.py
sw_rest_utils/tests.py
sw_rest_utils/views.py
sw_rest_utils.egg-info/PKG-INFO
sw_rest_utils.egg-info/SOURCES.txt
sw_rest_utils.egg-info/dependency_links.txt
sw_rest_utils.egg-info/requires.txt
sw_rest_utils.egg-info/top_level.txt