Metadata-Version: 1.0
Name: sw-rest-utils
Version: 0.0.25
Summary: Soft Way company REST utils.
Home-page: https://github.com/telminov/sw-rest-utils
Author: Telminov Sergey
Author-email: UNKNOWN
License: The MIT License
Platform: UNKNOWN
